deedee/__init__.py
deedee/deedee.py
deedee-0.1.dist-info/DESCRIPTION.rst
deedee-0.1.dist-info/METADATA
deedee-0.1.dist-info/RECORD
deedee-0.1.dist-info/WHEEL
deedee-0.1.dist-info/metadata.json
deedee-0.1.dist-info/top_level.txt
